{"location":"Boston MA","default_profile":false,"profile_background_tile":true,"statuses_count":4188,"lang":"en","profile_link_color":"0084B4","profile_banner_url":"https://pbs.twimg.com/profile_banners/14698049/1387144117","id":14698049,"following":true,"protected":false,"favourites_count":67,"profile_text_color":"333333","description":"Bitcoin enthusiast, Entrepreneur, Software dev & Data cruncher - Formerly Parisian now Bostonian crunching Analytics @Berkleeonline","verified":false,"contributors_enabled":false,"profile_sidebar_border_color":"FF6666","name":"Alex Perrier","profile_background_color":"FFFFFF","created_at":"Thu May 08 08:56:37 +0000 2008","is_translation_enabled":false,"default_profile_image":false,"followers_count":698,"profile_image_url_https":"https://pbs.twimg.com/profile_images/499307912825565184/nm1zZ9Yl_normal.jpeg","geo_enabled":true,"status":{"retweeted_status":{"contributors":null,"text":"New White Paper: \"The Bitcoin Blockchain\" by Director of Research @RonGlantz &amp; Venture Associate @AdmiralLeviathn http://t.co/18gEpZhCg6","geo":null,"retweeted":false,"in_reply_to_screen_name":null,"possibly_sensitive":false,"truncated":false,"lang":"en","entities":{"symbols":[],"urls":[{"expanded_url":"http://bit.ly/1q8U1al","indices":[118,140],"display_url":"bit.ly/1q8U1al","url":"http://t.co/18gEpZhCg6"}],"hashtags":[],"user_mentions":[{"id":2515887780,"name":"Ron Glantz","indices":[66,76],"screen_name":"RonGlantz","id_str":"2515887780"},{"id":2371415304,"name":"JD","indices":[101,117],"screen_name":"AdmiralLeviathn","id_str":"2371415304"}]},"in_reply_to_status_id_str":null,"id":506939112772096002,"source":"<a href=\"http://twitter.com\" rel=\"nofollow\">Twitter Web Client<\/a>","in_reply_to_user_id_str":null,"favorited":false,"in_reply_to_status_id":null,"retweet_count":28,"created_at":"Tue Sep 02 22:57:57 +0000 2014","in_reply_to_user_id":null,"favorite_count":30,"id_str":"506939112772096002","place":null,"coordinates":null},"contributors":null,"text":"RT @PanteraCapital: New White Paper: \"The Bitcoin Blockchain\" by Director of Research @RonGlantz &amp; Venture Associate @AdmiralLeviathn http:\u2026","geo":null,"retweeted":false,"in_reply_to_screen_name":null,"possibly_sensitive":false,"truncated":false,"lang":"en","entities":{"symbols":[],"urls":[{"expanded_url":"http://bit.ly/1q8U1al","indices":[143,144],"display_url":"bit.ly/1q8U1al","url":"http://t.co/18gEpZhCg6"}],"hashtags":[],"user_mentions":[{"id":2287471915,"name":"Pantera Capital","indices":[3,18],"screen_name":"PanteraCapital","id_str":"2287471915"},{"id":2515887780,"name":"Ron Glantz","indices":[86,96],"screen_name":"RonGlantz","id_str":"2515887780"},{"id":2371415304,"name":"JD","indices":[121,137],"screen_name":"AdmiralLeviathn","id_str":"2371415304"}]},"in_reply_to_status_id_str":null,"id":508326197466767360,"source":"<a href=\"http://twitter.com/download/iphone\" rel=\"nofollow\">Twitter for iPhone<\/a>","in_reply_to_user_id_str":null,"favorited":false,"in_reply_to_status_id":null,"retweet_count":28,"created_at":"Sat Sep 06 18:49:44 +0000 2014","in_reply_to_user_id":null,"favorite_count":0,"id_str":"508326197466767360","place":null,"coordinates":null},"profile_background_image_url":"http://pbs.twimg.com/profile_background_images/83533196/twilk_background_4b9f0b8a88f14.jpg","profile_background_image_url_https":"https://pbs.twimg.com/profile_background_images/83533196/twilk_background_4b9f0b8a88f14.jpg","follow_request_sent":false,"entities":{"description":{"urls":[]},"url":{"urls":[{"expanded_url":"http://linkedin.com/in/alexisperrier","indices":[0,22],"display_url":"linkedin.com/in/alexisperri\u2026","url":"http://t.co/9LqNpzj3Zu"}]}},"url":"http://t.co/9LqNpzj3Zu","utc_offset":-14400,"time_zone":"Eastern Time (US & Canada)","notifications":false,"profile_use_background_image":false,"friends_count":218,"profile_sidebar_fill_color":"FFFFFF","screen_name":"alexip","id_str":"14698049","profile_image_url":"http://pbs.twimg.com/profile_images/499307912825565184/nm1zZ9Yl_normal.jpeg","listed_count":40,"is_translator":false}