{"location":"","default_profile":true,"profile_background_tile":false,"statuses_count":317,"lang":"ru","profile_link_color":"0084B4","id":1376581021,"following":false,"protected":false,"favourites_count":58,"profile_text_color":"333333","description":"cryptocurrency investor/trader","verified":false,"contributors_enabled":false,"profile_sidebar_border_color":"C0DEED","name":"distresser","profile_background_color":"C0DEED","created_at":"Wed Apr 24 09:04:47 +0000 2013","is_translation_enabled":false,"default_profile_image":false,"followers_count":420,"profile_image_url_https":"https://pbs.twimg.com/profile_images/378800000769076612/a1ff4f2038d4ab12aff64dd3bea34a6c_normal.jpeg","geo_enabled":false,"status":{"retweeted_status":{"contributors":null,"text":"The Jinn dutch auction has closed! Thanks to all participants, expect exciting times ahead. #Jinn","geo":null,"retweeted":false,"in_reply_to_screen_name":null,"truncated":false,"lang":"en","entities":{"symbols":[],"urls":[],"hashtags":[{"text":"Jinn","indices":[92,97]}],"user_mentions":[]},"in_reply_to_status_id_str":null,"id":517413117463363586,"source":"<a href=\"http://twitter.com\" rel=\"nofollow\">Twitter Web Client<\/a>","in_reply_to_user_id_str":null,"favorited":false,"in_reply_to_status_id":null,"retweet_count":4,"created_at":"Wed Oct 01 20:37:54 +0000 2014","in_reply_to_user_id":null,"favorite_count":0,"id_str":"517413117463363586","place":null,"coordinates":null},"contributors":null,"text":"RT @jinnlabs: The Jinn dutch auction has closed! Thanks to all participants, expect exciting times ahead. #Jinn","geo":null,"retweeted":false,"in_reply_to_screen_name":null,"truncated":false,"lang":"en","entities":{"symbols":[],"urls":[],"hashtags":[{"text":"Jinn","indices":[106,111]}],"user_mentions":[{"id":2831171406,"name":"Jinn","indices":[3,12],"screen_name":"jinnlabs","id_str":"2831171406"}]},"in_reply_to_status_id_str":null,"id":517563075181158401,"source":"<a href=\"http://twitter.com/download/android\" rel=\"nofollow\">Twitter for Android<\/a>","in_reply_to_user_id_str":null,"favorited":false,"in_reply_to_status_id":null,"retweet_count":4,"created_at":"Thu Oct 02 06:33:47 +0000 2014","in_reply_to_user_id":null,"favorite_count":0,"id_str":"517563075181158401","place":null,"coordinates":null},"profile_background_image_url":"http://abs.twimg.com/images/themes/theme1/bg.png","profile_background_image_url_https":"https://abs.twimg.com/images/themes/theme1/bg.png","follow_request_sent":false,"entities":{"description":{"urls":[]}},"url":null,"utc_offset":null,"time_zone":null,"notifications":false,"profile_use_background_image":true,"friends_count":247,"profile_sidebar_fill_color":"DDEEF6","screen_name":"distresser","id_str":"1376581021","profile_image_url":"http://pbs.twimg.com/profile_images/378800000769076612/a1ff4f2038d4ab12aff64dd3bea34a6c_normal.jpeg","listed_count":2,"is_translator":false}