{"location":"Investment Citadel","default_profile":true,"profile_background_tile":false,"statuses_count":459,"lang":"en","profile_link_color":"0084B4","profile_banner_url":"https://pbs.twimg.com/profile_banners/2768000832/1409382406","id":2768000832,"following":true,"protected":false,"favourites_count":34,"profile_text_color":"333333","description":"Professional economist and forex trader. Leveraged trading and liquidity swaps. Marketwatch 24/7 365 BTC/ALTS. DYOR.  Thanks Satoshi","verified":false,"contributors_enabled":false,"profile_sidebar_border_color":"C0DEED","name":"Crypto God","profile_background_color":"C0DEED","created_at":"Mon Aug 25 21:42:10 +0000 2014","is_translation_enabled":false,"default_profile_image":false,"followers_count":3614,"profile_image_url_https":"https://pbs.twimg.com/profile_images/505611816211206144/pw0w6WfS_normal.jpeg","geo_enabled":false,"status":{"contributors":null,"text":"@smokin35 @moolah_io should they rather take the hit themselves of paying a code reviewer? nah, I think that lies with the dev to sort out.","geo":null,"retweeted":false,"in_reply_to_screen_name":"smokin35","truncated":false,"lang":"en","entities":{"symbols":[],"urls":[],"hashtags":[],"user_mentions":[{"id":2360105966,"name":"Gw3","indices":[0,9],"screen_name":"smokin35","id_str":"2360105966"},{"id":2272208143,"name":"Moolah","indices":[10,20],"screen_name":"moolah_io","id_str":"2272208143"}]},"in_reply_to_status_id_str":"508302660664299520","id":508303360609767424,"source":"<a href=\"http://twitter.com\" rel=\"nofollow\">Twitter Web Client<\/a>","in_reply_to_user_id_str":"2360105966","favorited":false,"in_reply_to_status_id":508302660664299520,"retweet_count":0,"created_at":"Sat Sep 06 17:18:59 +0000 2014","in_reply_to_user_id":2360105966,"favorite_count":0,"id_str":"508303360609767424","place":null,"coordinates":null},"profile_background_image_url":"http://abs.twimg.com/images/themes/theme1/bg.png","profile_background_image_url_https":"https://abs.twimg.com/images/themes/theme1/bg.png","follow_request_sent":false,"entities":{"description":{"urls":[]}},"url":null,"utc_offset":7200,"time_zone":"Ljubljana","notifications":false,"profile_use_background_image":true,"friends_count":2139,"profile_sidebar_fill_color":"DDEEF6","screen_name":"Cryptology101","id_str":"2768000832","profile_image_url":"http://pbs.twimg.com/profile_images/505611816211206144/pw0w6WfS_normal.jpeg","listed_count":2,"is_translator":false}