{"location":"Silicon Valley","default_profile":false,"profile_background_tile":true,"statuses_count":1560,"lang":"en","profile_link_color":"0084B4","profile_banner_url":"https://pbs.twimg.com/profile_banners/1952836374/1405454497","id":1952836374,"following":true,"protected":false,"favourites_count":2000,"profile_text_color":"333333","description":"Co-Organizer of Silicon Valley #Bitcoin, Biz Dev, Marketing & Leading Plug and Play's Bitcoin Accelerator: http://t.co/w0xdW839wA |  #Plugin, #Fishing","verified":false,"contributors_enabled":false,"profile_sidebar_border_color":"000000","name":"Scott Robinson","profile_background_color":"F5F8FA","created_at":"Thu Oct 10 23:46:40 +0000 2013","is_translation_enabled":false,"default_profile_image":false,"followers_count":788,"profile_image_url_https":"https://pbs.twimg.com/profile_images/489137394461863936/a_cCabec_normal.png","geo_enabled":false,"status":{"contributors":null,"text":"#Bitcoin is hiring! Not only that: get paid with it! Story: http://t.co/bDaUT773B1 @Coinality #startups @Bitwage","geo":null,"retweeted":false,"in_reply_to_screen_name":null,"possibly_sensitive":false,"truncated":false,"lang":"en","entities":{"symbols":[],"urls":[{"expanded_url":"http://bit.ly/1nAIUCr","indices":[60,82],"display_url":"bit.ly/1nAIUCr","url":"http://t.co/bDaUT773B1"}],"hashtags":[{"text":"Bitcoin","indices":[0,8]},{"text":"startups","indices":[94,103]}],"user_mentions":[{"id":1458005406,"name":"Coinality","indices":[83,93],"screen_name":"Coinality","id_str":"1458005406"},{"id":2368346192,"name":"Bitwage","indices":[104,112],"screen_name":"Bitwage","id_str":"2368346192"}]},"in_reply_to_status_id_str":null,"id":507943029949210624,"source":"<a href=\"http://twitter.com\" rel=\"nofollow\">Twitter Web Client<\/a>","in_reply_to_user_id_str":null,"favorited":false,"in_reply_to_status_id":null,"retweet_count":4,"created_at":"Fri Sep 05 17:27:10 +0000 2014","in_reply_to_user_id":null,"favorite_count":6,"id_str":"507943029949210624","place":null,"coordinates":null},"profile_background_image_url":"http://pbs.twimg.com/profile_background_images/378800000153194253/pjCwKZ-Z.png","profile_background_image_url_https":"https://pbs.twimg.com/profile_background_images/378800000153194253/pjCwKZ-Z.png","follow_request_sent":false,"entities":{"description":{"urls":[{"expanded_url":"http://bit.ly/1kWckc6","indices":[107,129],"display_url":"bit.ly/1kWckc6","url":"http://t.co/w0xdW839wA"}]},"url":{"urls":[{"expanded_url":"http://bit.ly/1kKrNkf","indices":[0,22],"display_url":"bit.ly/1kKrNkf","url":"http://t.co/IqFmXCwtZS"}]}},"url":"http://t.co/IqFmXCwtZS","utc_offset":null,"time_zone":null,"notifications":false,"profile_use_background_image":true,"friends_count":275,"profile_sidebar_fill_color":"DDEEF6","screen_name":"TheScottRob","id_str":"1952836374","profile_image_url":"http://pbs.twimg.com/profile_images/489137394461863936/a_cCabec_normal.png","listed_count":35,"is_translator":false}